{
	"info": {
		"_postman_id": "876f7a5b-4148-4b82-91b5-ce0d23374880",
		"name": "Capston",
		"schema": "https://schema.getpostman.com/json/collection/v2.1.0/collection.json"
	},
	"item": [
		{
			"name": "Post actors",
			"request": {
				"auth": {
					"type": "bearer",
					"bearer": [
						{
							"key": "token",
							"value": "{{PRODUCER_TOKEN}}",
							"type": "string"
						}
					]
				},
				"method": "POST",
				"header": [],
				"body": {
					"mode": "raw",
					"raw": "{\r\n    \"name\": \"Ali\",\r\n    \"age\": \"39\",\r\n    \"gender\": \"male\"\r\n    \r\n}",
					"options": {
						"raw": {
							"language": "json"
						}
					}
				},
				"url": {
					"raw": "http://localhost:5000/actors",
					"protocol": "http",
					"host": [
						"localhost"
					],
					"port": "5000",
					"path": [
						"actors"
					]
				}
			},
			"response": []
		},
		{
			"name": "Get actor",
			"request": {
				"auth": {
					"type": "bearer",
					"bearer": [
						{
							"key": "token",
							"value": "{{PRODUCER_TOKEN}}",
							"type": "string"
						}
					]
				},
				"method": "GET",
				"header": [],
				"url": {
					"raw": "http://localhost:5000/actors",
					"protocol": "http",
					"host": [
						"localhost"
					],
					"port": "5000",
					"path": [
						"actors"
					]
				}
			},
			"response": []
		},
		{
			"name": "Post movie",
			"request": {
				"auth": {
					"type": "bearer",
					"bearer": [
						{
							"key": "token",
							"value": "{{PRODUCER_TOKEN}}",
							"type": "string"
						}
					]
				},
				"method": "POST",
				"header": [],
				"body": {
					"mode": "raw",
					"raw": "{\r\n    \"title\": \" saw \",\r\n    \"release_date\": \"2009\"\r\n}",
					"options": {
						"raw": {
							"language": "json"
						}
					}
				},
				"url": {
					"raw": "http://localhost:5000/movies",
					"protocol": "http",
					"host": [
						"localhost"
					],
					"port": "5000",
					"path": [
						"movies"
					]
				}
			},
			"response": []
		},
		{
			"name": "Delete actor",
			"request": {
				"auth": {
					"type": "bearer",
					"bearer": [
						{
							"key": "token",
							"value": "{{PRODUCER_TOKEN}}",
							"type": "string"
						}
					]
				},
				"method": "DELETE",
				"header": [],
				"url": {
					"raw": "http://localhost:5000/movies/1",
					"protocol": "http",
					"host": [
						"localhost"
					],
					"port": "5000",
					"path": [
						"movies",
						"1"
					]
				}
			},
			"response": []
		},
		{
			"name": "Get movies",
			"request": {
				"auth": {
					"type": "bearer",
					"bearer": [
						{
							"key": "token",
							"value": "{{PRODUCER_TOKEN}}",
							"type": "string"
						}
					]
				},
				"method": "GET",
				"header": [],
				"url": {
					"raw": "http://localhost:5000/movies",
					"protocol": "http",
					"host": [
						"localhost"
					],
					"port": "5000",
					"path": [
						"movies"
					]
				}
			},
			"response": []
		},
		{
			"name": "Patch actor",
			"request": {
				"auth": {
					"type": "bearer",
					"bearer": [
						{
							"key": "token",
							"value": "{{PRODUCER_TOKEN}}",
							"type": "string"
						}
					]
				},
				"method": "PATCH",
				"header": [],
				"body": {
					"mode": "raw",
					"raw": "{\r\n    \"name\": \"new name\",\r\n    \"age\": 11,\r\n    \"gender\": \"Male\"\r\n}",
					"options": {
						"raw": {
							"language": "json"
						}
					}
				},
				"url": {
					"raw": "http://localhost:5000/actors/1",
					"protocol": "http",
					"host": [
						"localhost"
					],
					"port": "5000",
					"path": [
						"actors",
						"1"
					]
				}
			},
			"response": []
		},
		{
			"name": "Patch movies",
			"request": {
				"auth": {
					"type": "bearer",
					"bearer": [
						{
							"key": "token",
							"value": "{{PRODUCER_TOKEN}}",
							"type": "string"
						}
					]
				},
				"method": "PATCH",
				"header": [],
				"body": {
					"mode": "raw",
					"raw": "{\r\n    \"title\": \"step up 4\",\r\n    \"release_date\": \"2016\"\r\n}",
					"options": {
						"raw": {
							"language": "json"
						}
					}
				},
				"url": {
					"raw": "http://localhost:5000/movies/1",
					"protocol": "http",
					"host": [
						"localhost"
					],
					"port": "5000",
					"path": [
						"movies",
						"1"
					]
				}
			},
			"response": []
		},
		{
			"name": "Delete movie",
			"request": {
				"method": "GET",
				"header": [],
				"url": null
			},
			"response": []
		}
	]
}